.foundryrc
.gitignore
.travis.yml
CHANGELOG.rst
MANIFEST.in
README.rst
UNLICENSE
Vagrantfile
release.sh
requirements-dev.txt
requirements.txt
setup.py
test.sh
sublime_harness/__init__.py
sublime_harness/logger.py
sublime_harness/sublime_harness.py
sublime_harness.egg-info/PKG-INFO
sublime_harness.egg-info/SOURCES.txt
sublime_harness.egg-info/dependency_links.txt
sublime_harness.egg-info/pbr.json
sublime_harness.egg-info/requires.txt
sublime_harness.egg-info/top_level.txt
sublime_harness/launchers/__init__.py
sublime_harness/launchers/command.py
sublime_harness/launchers/init.py