Metadata-Version: 1.1
Name: sublime-harness
Version: 0.4.2
Summary: Run Python in Sublime Text from outside of Sublime Text
Home-page: https://github.com/twolfson/sublime-harness
Author: Todd Wolfson
Author-email: todd@twolfson.com
License: UNLICENSE
Download-URL: https://github.com/twolfson/sublime-harness/archive/master.zip
Keywords: sublime text,harness,runner
Platform: UNKNOWN
Classifier: Development Status :: 3 - Alpha
Classifier: Intended Audience :: Developers
Classifier: License :: Public Domain
Classifier: Operating System :: OS Independent
Classifier: Programming Language :: Python
Classifier: Topic :: Text Editors
